matrixObj/Matrix.py
matrixObj/__init__.py
matrixObj-1.2.1.dist-info/LICENSE
matrixObj-1.2.1.dist-info/METADATA
matrixObj-1.2.1.dist-info/WHEEL
matrixObj-1.2.1.dist-info/top_level.txt
matrixObj-1.2.1.dist-info/RECORD
