Metadata-Version: 2.1
Name: matrixObj
Version: 1.2.1
Summary: A simple matrix module for basic matrix mathematical operations
Home-page: https://github.com/SpecialDude/matrixObj
Author: Warith Adetayo
Author-email: warithadetayo.awa@gmail.com
License: MIT
Platform: UNKNOWN
Classifier: Programming Language :: Python :: 3
Classifier: License :: OSI Approved :: MIT License
Classifier: Operating System :: OS Independent
Requires-Python: >=3
License-File: LICENSE
